fogledgerIndy/IndyBasic.py
fogledgerIndy/Node.py
fogledgerIndy/__init__.py
fogLedgerIndy-1.0.0.dist-info/LICENSE.txt
fogLedgerIndy-1.0.0.dist-info/METADATA
fogLedgerIndy-1.0.0.dist-info/WHEEL
fogLedgerIndy-1.0.0.dist-info/top_level.txt
fogLedgerIndy-1.0.0.dist-info/RECORD
